Metadata-Version: 1.0
Name: allocGPUs
Version: 0.0.7
Summary: A Python library that automatically sets multiple gpus.
Home-page: UNKNOWN
Author: UNKNOWN
Author-email: UNKNOWN
License: Public Domain
Platform: any
